{
    "keep": {
        "days": true,
        "amount": 14
    },
    "auditLog": "log\\.35035b3dc1b769d4982bc67bd65a1593fcef260d-audit.json",
    "files": [
        {
            "date": 1651195448012,
            "name": "log\\app-error-2022-04-29.log",
            "hash": "a963b4181b3ffadbf9495eb86a92ddd5"
        },
        {
            "date": 1652341228767,
            "name": "log\\app-error-2022-05-12.log",
            "hash": "ab545cebf624de01d65a899bf3c6eaee"
        }
    ],
    "hashType": "md5"
}